rw_api1-1.0.3.dist-info/DESCRIPTION.rst
rw_api1-1.0.3.dist-info/METADATA
rw_api1-1.0.3.dist-info/RECORD
rw_api1-1.0.3.dist-info/WHEEL
rw_api1-1.0.3.dist-info/metadata.json
rw_api1-1.0.3.dist-info/top_level.txt
rw_api_tools/__init__.py
rw_api_tools/rw_api_tools.py
